{"orderBooks":[{"baseAsset":"ETH","bids":[],"asks":[],"lastTradeId":0,"currentPrice":0},{"baseAsset":"BTC","bids":[{"id":"mp26larqigdn6o1ccksgaj","side":"buy","price":499,"quantity":5,"userId":"680f97bce5fd097d40155914","clientOrderId":"ord_aywjcjyfg1m","filled":22,"timeInForce":"GTC","type":"market","timestamp":1745933602469}],"asks":[{"id":"2nb7x0cay9ajtbvpi69chj","side":"sell","price":468,"quantity":10,"userId":"6807748cba57203f73b4dd5f","clientOrderId":"ord_11hedm9sdsws","filled":7,"timeInForce":"GTC","type":"market","timestamp":1745938478986}],"lastTradeId":0,"currentPrice":0},{"baseAsset":"SOL","bids":[],"asks":[],"lastTradeId":0,"currentPrice":0},{"baseAsset":"ETH","bids":[],"asks":[],"lastTradeId":0,"currentPrice":0},{"baseAsset":"BTC","bids":[],"asks":[],"lastTradeId":0,"currentPrice":0},{"baseAsset":"SOL","bids":[],"asks":[],"lastTradeId":0,"currentPrice":0},{"baseAsset":"AAPL","bids":[],"asks":[],"lastTradeId":0,"currentPrice":0},{"baseAsset":"GOOGL","bids":[],"asks":[],"lastTradeId":0,"currentPrice":0},{"baseAsset":"AMZN","bids":[],"asks":[],"lastTradeId":0,"currentPrice":0},{"baseAsset":"MSFT","bids":[],"asks":[],"lastTradeId":0,"currentPrice":0},{"baseAsset":"META","bids":[],"asks":[],"lastTradeId":0,"currentPrice":0},{"baseAsset":"NFLX","bids":[],"asks":[],"lastTradeId":0,"currentPrice":0},{"baseAsset":"TSLA","bids":[],"asks":[],"lastTradeId":0,"currentPrice":0},{"baseAsset":"NVDA","bids":[],"asks":[],"lastTradeId":0,"currentPrice":0},{"baseAsset":"AMD","bids":[],"asks":[],"lastTradeId":0,"currentPrice":0},{"baseAsset":"INTC","bids":[],"asks":[],"lastTradeId":0,"currentPrice":0},{"baseAsset":"BABA","bids":[],"asks":[],"lastTradeId":0,"currentPrice":0},{"baseAsset":"UBER","bids":[],"asks":[],"lastTradeId":0,"currentPrice":0},{"baseAsset":"LYFT","bids":[],"asks":[],"lastTradeId":0,"currentPrice":0},{"baseAsset":"DIS","bids":[],"asks":[],"lastTradeId":0,"currentPrice":0},{"baseAsset":"SONY","bids":[],"asks":[],"lastTradeId":0,"currentPrice":0},{"baseAsset":"PEP","bids":[],"asks":[],"lastTradeId":0,"currentPrice":0},{"baseAsset":"KO","bids":[],"asks":[],"lastTradeId":0,"currentPrice":0},{"baseAsset":"PFE","bids":[],"asks":[],"lastTradeId":0,"currentPrice":0},{"baseAsset":"JNJ","bids":[],"asks":[],"lastTradeId":0,"currentPrice":0},{"baseAsset":"MRNA","bids":[],"asks":[],"lastTradeId":0,"currentPrice":0},{"baseAsset":"T","bids":[],"asks":[],"lastTradeId":0,"currentPrice":0},{"baseAsset":"VZ","bids":[],"asks":[],"lastTradeId":0,"currentPrice":0},{"baseAsset":"WMT","bids":[],"asks":[],"lastTradeId":0,"currentPrice":0},{"baseAsset":"COST","bids":[],"asks":[],"lastTradeId":0,"currentPrice":0},{"baseAsset":"SHOP","bids":[],"asks":[],"lastTradeId":0,"currentPrice":0},{"baseAsset":"ADBE","bids":[],"asks":[],"lastTradeId":0,"currentPrice":0},{"baseAsset":"CRM","bids":[],"asks":[],"lastTradeId":0,"currentPrice":0}],"userBalances":[["6807748cba57203f73b4dd5f",{"USDC":{"available":9999647196,"locked":269377.9999999999},"BTC":{"available":85821,"locked":14060}}],["680f97bce5fd097d40155914",{"USDC":{"available":35011,"locked":-5392},"BTC":{"available":41,"locked":0}}]]}